[{"id":1,"first_name":"Anabelle","last_name":"Maha","email":"amaha0@economist.com","company_name":"Photobug","designation":"legal","address":"9 Debra Parkway","phone_number":"1984448417","date":"01/11/2022","city":"Santo Domingo"},
{"id":2,"first_name":"Christie","last_name":"Scutchings","email":"cscutchings1@w3.org","company_name":"Twitterlist","designation":"Research and Development","address":"3 Golden Leaf Crossing","phone_number":"4292360505","date":"04/11/2022","city":"Dhahab"},
{"id":3,"first_name":"Guillermo","last_name":"Walwood","email":"gwalwood2@slashdot.org","company_name":"Dazzlesphere","designation":"Training","address":"9853 Gina Drive","phone_number":"1472162504","date":"07/11/2022","city":"Pashkovskiy"},
{"id":4,"first_name":"Dulce","last_name":"Geke","email":"dgeke3@deliciousdays.com","company_name":"Meejo","designation":"Services","address":"109 Anzinger Circle","phone_number":"2125581799","date":"07/11/2022","city":"Maromme","state":"Haute-Normandie"},
{"id":5,"first_name":"Reina","last_name":"Blincow","email":"rblincow4@comsenz.com","company_name":"Browsecat","designation":"Human Resources","address":"96343 Victoria Drive","phone_number":"6668471142","date":"06/11/2022","city":"Jingxi"},
{"id":6,"first_name":"Brannon","last_name":"Blazewicz","email":"bblazewicz5@addthis.com","company_name":"Browsezoom","designation":"Support","address":"88515 Spenser Alley","phone_number":"2957115171","date":"05/11/2022","city":"Warungbanten"},
{"id":7,"first_name":"Germain","last_name":"Wipfler","email":"gwipfler6@myspace.com","company_name":"Edgepulse","designation":"Marketing","address":"85 Hanover Point","phone_number":"4044109128","date":"02/11/2022","city":"Atlanta","state":"Georgia"},
{"id":8,"first_name":"Carroll","last_name":"Rastall","email":"crastall7@bbc.co.uk","company_name":"Kanoodle","designation":"Marketing","address":"45483 Fremont Plaza","phone_number":"5688816541","date":"03/11/2022","city":"Platičevo"},
{"id":9,"first_name":"Bobby","last_name":"Chettle","email":"bchettle8@topsy.com","company_name":"Bubbletube","designation":"Legal","address":"61816 Sachtjen Way","phone_number":"3827621664","date":"06/11/2022","city":"Tabinay"},
{"id":10,"first_name":"Jerri","last_name":"Birts","email":"jbirts9@merriam-webster.com","company_name":"Buzzster","designation":"Business Development","address":"482 Rutledge Parkway","phone_number":"2193126912","date":"07/11/2022","city":"Chiscas"},
{"id":11,"first_name":"Sonya","last_name":"Clementel","email":"sclementela@nydailynews.com","company_name":"Teklist","designation":"Services","address":"95222 Macpherson Lane","phone_number":"3391847679","date":"04/11/2022","city":"Błonie"},
{"id":12,"first_name":"Roi","last_name":"Scad","email":"rscadb@canalblog.com","company_name":"Yozio","designation":"Engineering","address":"50 Kensington Terrace","phone_number":"4267099194","date":"03/11/2022","city":"Milići"},
{"id":13,"first_name":"Concettina","last_name":"Neenan","email":"cneenanc@eepurl.com","company_name":"Youopia","designation":"Human Resources","address":"577 Dovetail Parkway","phone_number":"2749667862","date":"02/11/2022","city":"Afogados da Ingazeira"},
{"id":14,"first_name":"Fayre","last_name":"Airton","email":"fairtond@studiopress.com","company_name":"Divape","designation":"Accounting","address":"727 Karstens Road","phone_number":"5753139225","date":"05/11/2022","city":"Aguelmous"},
{"id":15,"first_name":"Valentine","last_name":"Robken","email":"vrobkene@infoseek.co.jp","company_name":"Browsecat","designation":"Business Development","address":"3 Norway Maple Terrace","phone_number":"9683708068","date":"01/11/2022","city":"Kinmparana"},
{"id":16,"first_name":"Carlen","last_name":"Ridolfi","email":"cridolfif@disqus.com","company_name":"Browseblab","designation":"Training","address":"34970 Nova Way","phone_number":"6273139171","date":"05/11/2022","city":"Pieńsk"},
{"id":17,"first_name":"Maryanna","last_name":"Bransden","email":"mbransdeng@rambler.ru","company_name":"Linklinks","designation":"Engineering","address":"848 Heath Place","phone_number":"2978846917","date":"02/11/2022","city":"Baziqiao"},
{"id":18,"first_name":"Kipp","last_name":"Simcoe","email":"ksimcoeh@hubpages.com","company_name":"Divavu","designation":"Product Management","address":"600 John Wall Road","phone_number":"1092374620","date":"03/11/2022","city":"Ribeiro","state":"Vila Real"},
{"id":19,"first_name":"Lurlene","last_name":"Snuggs","email":"lsnuggsi@youtube.com","company_name":"Zoozzy","designation":"Training","address":"88 Sage Point","phone_number":"8514104954","date":"03/11/2022","city":"North York","state":"Ontario"},
{"id":20,"first_name":"Enos","last_name":"Gaythwaite","email":"egaythwaitej@dagondesign.com","company_name":"Skivee","designation":"Marketing","address":"0784 Loomis Road","phone_number":"4558570251","date":"03/11/2022","city":"Tanagara"},
{"id":21,"first_name":"Evy","last_name":"Kobpa","email":"ekobpak@t.co","company_name":"Tavu","designation":"Human Resources","address":"3812 Rowland Alley","phone_number":"9657611869","date":"06/11/2022","city":"Santiago De Compostela","state":"Galicia"},
{"id":22,"first_name":"Margalo","last_name":"Gother","email":"mgotherl@51.la","company_name":"Wordpedia","designation":"Marketing","address":"175 Summer Ridge Way","phone_number":"7588360144","date":"05/11/2022","city":"La Esperanza","state":"Veracruz Llave"},
{"id":23,"first_name":"Nye","last_name":"Grace","email":"ngracem@google.it","company_name":"Linktype","designation":"Research and Development","address":"0 Chinook Drive","phone_number":"6947784039","date":"05/11/2022","city":"Suwalan"},
{"id":24,"first_name":"Danell","last_name":"Mattke","email":"dmattken@house.gov","company_name":"Zoombeat","designation":"Services","address":"69 Dottie Trail","phone_number":"3771001825","date":"03/11/2022","city":"Stockholm","state":"Stockholm"},
{"id":25,"first_name":"Stefanie","last_name":"Levison","email":"slevisono@facebook.com","company_name":"Trupe","designation":"Business Development","address":"17734 Prentice Avenue","phone_number":"3911905958","date":"02/11/2022","city":"Dingbu"},
{"id":26,"first_name":"Sheena","last_name":"Costerd","email":"scosterdp@printfriendly.com","company_name":"Wikivu","designation":"Human Resources","address":"87770 Union Lane","phone_number":"8768487784","date":"04/11/2022","city":"Utena"},
{"id":27,"first_name":"Sorcha","last_name":"McGuffog","email":"smcguffogq@about.me","company_name":"Twiyo","designation":"Engineering","address":"024 Superior Junction","phone_number":"8037755255","date":"01/11/2022","city":"Valdivia"},
{"id":28,"first_name":"Elane","last_name":"Ziemens","email":"eziemensr@prweb.com","company_name":"Trilia","designation":"Research and Development","address":"98 Merrick Point","phone_number":"2981356975","date":"04/11/2022","city":"Xunqiao"},
{"id":29,"first_name":"Lazaro","last_name":"Orrell","email":"lorrells@about.com","company_name":"Voomm","designation":"Accounting","address":"5 Del Mar Parkway","phone_number":"4071945097","date":"05/11/2022","city":"Lypova Dolyna"},
{"id":30,"first_name":"Obadias","last_name":"Cadwell","email":"ocadwellt@pagesperso-orange.fr","company_name":"Tagpad","designation":"Product Management","address":"1919 Sommers Court","phone_number":"7728174561","date":"07/11/2022","city":"Nova Venécia"},
{"id":31,"first_name":"Hodge","last_name":"Fahy","email":"hfahyu@ucla.edu","company_name":"Edgetag","designation":"Human Resources","address":"7665 Kingsford Drive","phone_number":"4705419360","date":"07/11/2022","city":"Ambulong"},
{"id":32,"first_name":"Britta","last_name":"Taffley","email":"btaffleyv@privacy.gov.au","company_name":"Flipopia","designation":"Research and Development","address":"63 Schurz Circle","phone_number":"2339312946","date":"01/11/2022","city":"Alaminos"},
{"id":33,"first_name":"Simonne","last_name":"Janos","email":"sjanosw@imageshack.us","company_name":"Wikizz","designation":"Legal","address":"6 Brentwood Court","phone_number":"6157884306","date":"07/11/2022","city":"Staroyur’yevo"},
{"id":34,"first_name":"Christabel","last_name":"Goracci","email":"cgoraccix@ebay.co.uk","company_name":"Quinu","designation":"Accounting","address":"68 Huxley Trail","phone_number":"5234448109","date":"02/11/2022","city":"Semīrom"},
{"id":35,"first_name":"Deanna","last_name":"Kroon","email":"dkroony@sogou.com","company_name":"Kazu","designation":"Product Management","address":"280 Ohio Place","phone_number":"8811244185","date":"05/11/2022","city":"Omemee","state":"Ontario"},
{"id":36,"first_name":"Reynolds","last_name":"Kensington","email":"rkensingtonz@tripod.com","company_name":"Trudoo","designation":"Accounting","address":"6317 Thierer Drive","phone_number":"9729938906","date":"06/11/2022","city":"Ressano Garcia"},
{"id":37,"first_name":"Davon","last_name":"Maynell","email":"dmaynell10@booking.com","company_name":"Npath","designation":"Human Resources","address":"11690 Scofield Crossing","phone_number":"4171109957","date":"03/11/2022","city":"Mehona"},
{"id":38,"first_name":"Marika","last_name":"Critch","email":"mcritch11@zimbio.com","company_name":"Reallinks","designation":"Human Resources","address":"0 Steensland Crossing","phone_number":"6583784676","date":"05/11/2022","city":"Mehona"},
{"id":39,"first_name":"Giffer","last_name":"Kenningley","email":"gkenningley12@imdb.com","company_name":"Kwilith","designation":"Legal","address":"3 Shoshone Circle","phone_number":"6473777359","date":"07/11/2022","city":"Mor Laok"},
{"id":40,"first_name":"Gardiner","last_name":"Balkwill","email":"gbalkwill13@mac.com","company_name":"Buzzdog","designation":"Accounting","address":"5751 Eagle Crest Street","phone_number":"1591451784","date":"07/11/2022","city":"Sabon Gari-Nangere"},
{"id":41,"first_name":"Sabina","last_name":"Nosworthy","email":"snosworthy14@google.ru","company_name":"Quamba","designation":"Business Development","address":"8442 Bultman Crossing","phone_number":"4492701398","date":"07/11/2022","city":"Parapat"},
{"id":42,"first_name":"Thibaud","last_name":"Mattingson","email":"tmattingson15@histats.com","company_name":"Trilith","designation":"Engineering","address":"1 Lake View Point","phone_number":"7667699810","date":"02/11/2022","city":"Kinloch","state":"Scotland"},
{"id":43,"first_name":"Giselbert","last_name":"Langworthy","email":"glangworthy16@umich.edu","company_name":"Feedfire","designation":"Marketing","address":"64355 Lunder Hill","phone_number":"1941367836","date":"01/11/2022","city":"Paltashaco"},
{"id":44,"first_name":"Benjamin","last_name":"Sesons","email":"bsesons17@yellowbook.com","company_name":"Devpulse","designation":"Services","address":"7568 Loeprich Park","phone_number":"6565661245","date":"01/11/2022","city":"Huaniao"},
{"id":45,"first_name":"Kathi","last_name":"Roelvink","email":"kroelvink18@moonfruit.com","company_name":"Skipstorm","designation":"Training","address":"82 Village Point","phone_number":"2041404285","date":"01/11/2022","city":"Quatro Barras"},
{"id":46,"first_name":"Cher","last_name":"Riach","email":"criach19@paypal.com","company_name":"Vinte","designation":"Research and Development","address":"2 Forest Run Road","phone_number":"9698281017","date":"04/11/2022","city":"Tilang"},
{"id":47,"first_name":"Lucian","last_name":"Lean","email":"llean1a@indiatimes.com","company_name":"Kwilith","designation":"Marketing","address":"8970 Vidon Hill","phone_number":"3737763594","date":"05/11/2022","city":"Fresno"},
{"id":48,"first_name":"Jessey","last_name":"Tolliday","email":"jtolliday1b@opensource.org","company_name":"Browseblab","designation":"Legal","address":"368 Golf Way","phone_number":"5641076554","date":"04/11/2022","city":"Baozi"},
{"id":49,"first_name":"Dayle","last_name":"Roderham","email":"droderham1c@reverbnation.com","company_name":"Quatz","designation":"Marketing","address":"2903 Dryden Trail","phone_number":"9517581079","date":"03/11/2022","city":"Yixi"},
{"id":50,"first_name":"Alessandro","last_name":"Dyos","email":"adyos1d@artisteer.com","company_name":"Yoveo","designation":"Accounting","address":"576 Northview Plaza","phone_number":"8271512232","date":"01/11/2022","city":"Yefremov"},
{"id":51,"first_name":"Karena","last_name":"Swan","email":"kswan1e@posterous.com","company_name":"Fivebridge","designation":"Research and Development","address":"5 2nd Park","phone_number":"5871572817","date":"05/11/2022","city":"Lidian"},
{"id":52,"first_name":"Nat","last_name":"Allender","email":"nallender1f@nhs.uk","company_name":"Oodoo","designation":"Services","address":"44554 Pine View Alley","phone_number":"6473896805","date":"07/11/2022","city":"Wengang"},
{"id":53,"first_name":"Jania","last_name":"Cater","email":"jcater1g@goo.gl","company_name":"Skilith","designation":"Sales","address":"9 South Trail","phone_number":"7327454045","date":"02/11/2022","city":"Leipzig","state":"Sachsen"},
{"id":54,"first_name":"Genia","last_name":"Arson","email":"garson1h@washington.edu","company_name":"Wikizz","designation":"Engineering","address":"655 Troy Drive","phone_number":"5118066883","date":"03/11/2022","city":"Alvarães"},
{"id":55,"first_name":"Bradford","last_name":"Alwell","email":"balwell1i@istockphoto.com","company_name":"Trilia","designation":"Accounting","address":"958 Elmside Pass","phone_number":"1961761103","date":"04/11/2022","city":"Vassouras"},
{"id":56,"first_name":"Derwin","last_name":"Village","email":"dvillage1j@smugmug.com","company_name":"Rhycero","designation":"Legal","address":"91143 Ronald Regan Park","phone_number":"8295941343","date":"04/11/2022","city":"Acarí"},
{"id":57,"first_name":"Paulo","last_name":"Zannotti","email":"pzannotti1k@baidu.com","company_name":"Skalith","designation":"Product Management","address":"5 Kensington Avenue","phone_number":"3825828576","date":"03/11/2022","city":"Fukiage-fujimi"},
{"id":58,"first_name":"Windy","last_name":"Sturley","email":"wsturley1l@furl.net","company_name":"Realcube","designation":"Research and Development","address":"468 Warbler Parkway","phone_number":"5668876715","date":"02/11/2022","city":"Brylivka"},
{"id":59,"first_name":"Elyn","last_name":"Pavlik","email":"epavlik1m@dot.gov","company_name":"Viva","designation":"Training","address":"339 Grayhawk Parkway","phone_number":"3725294921","date":"01/11/2022","city":"Baochang"},
{"id":60,"first_name":"Jerri","last_name":"Baumadier","email":"jbaumadier1n@mapy.cz","company_name":"Eidel","designation":"Product Management","address":"564 Commercial Lane","phone_number":"2205786394","date":"03/11/2022","city":"Zhongxiang"},
{"id":61,"first_name":"Faun","last_name":"Fearnyhough","email":"ffearnyhough1o@mapy.cz","company_name":"Trudeo","designation":"Engineering","address":"9 Fordem Park","phone_number":"6804640715","date":"03/11/2022","city":"Gaibei"},
{"id":62,"first_name":"Leonardo","last_name":"De Filippo","email":"ldefilippo1p@netscape.com","company_name":"Centimia","designation":"Engineering","address":"8405 Grayhawk Circle","phone_number":"6859254666","date":"03/11/2022","city":"Kumanovo"},
{"id":63,"first_name":"Tamqrah","last_name":"Lung","email":"tlung1q@icio.us","company_name":"Realbridge","designation":"Legal","address":"01 Buell Crossing","phone_number":"9376152144","date":"05/11/2022","city":"Juḩr ad Dīk"},
{"id":64,"first_name":"Upton","last_name":"Death","email":"udeath1r@storify.com","company_name":"Ailane","designation":"Engineering","address":"11918 Gale Road","phone_number":"8261301182","date":"05/11/2022","city":"Sarvaš"},
{"id":65,"first_name":"Salvidor","last_name":"Jeenes","email":"sjeenes1s@biglobe.ne.jp","company_name":"Linkbuzz","designation":"Training","address":"21 Scott Drive","phone_number":"9599779608","date":"06/11/2022","city":"Thung Khru"},
{"id":66,"first_name":"Margit","last_name":"Bene","email":"mbene1t@java.com","company_name":"Oyoyo","designation":"Sales","address":"55 Lien Terrace","phone_number":"9723718058","date":"03/11/2022","city":"Khemisset"},
{"id":67,"first_name":"Gavrielle","last_name":"Scotsbrook","email":"gscotsbrook1u@eepurl.com","company_name":"Dablist","designation":"Services","address":"83546 Main Point","phone_number":"4563352014","date":"02/11/2022","city":"Reisjärvi"},
{"id":68,"first_name":"Hillery","last_name":"Di Ruggiero","email":"hdiruggiero1v@goo.gl","company_name":"Edgewire","designation":"Training","address":"762 Farragut Plaza","phone_number":"1137703008","date":"07/11/2022","city":"Senggapi"},
{"id":69,"first_name":"Kristian","last_name":"Blachford","email":"kblachford1w@hostgator.com","company_name":"Fivechat","designation":"Support","address":"81794 Annamark Hill","phone_number":"5562455938","date":"02/11/2022","city":"Yarīm"},
{"id":70,"first_name":"Say","last_name":"Capeloff","email":"scapeloff1x@printfriendly.com","company_name":"Tazzy","designation":"Accounting","address":"2879 Corscot Circle","phone_number":"6916396373","date":"01/11/2022","city":"Alingsås","state":"Västra Götaland"},
{"id":71,"first_name":"Tomkin","last_name":"Ommundsen","email":"tommundsen1y@smh.com.au","company_name":"Livefish","designation":"Engineering","address":"915 John Wall Pass","phone_number":"6353821937","date":"07/11/2022","city":"Valera"},
{"id":72,"first_name":"Remus","last_name":"Monan","email":"rmonan1z@shop-pro.jp","company_name":"Feednation","designation":"Services","address":"15853 Grim Junction","phone_number":"1596811035","date":"01/11/2022","city":"Tamboril"},
{"id":73,"first_name":"Keary","last_name":"Ringer","email":"kringer20@infoseek.co.jp","company_name":"Babbleset","designation":"Legal","address":"1 Ronald Regan Park","phone_number":"6178270232","date":"03/11/2022","city":"Guanmiao"},
{"id":74,"first_name":"Cris","last_name":"Edney","email":"cedney21@rediff.com","company_name":"Meetz","designation":"Product Management","address":"647 Ruskin Pass","phone_number":"8614609237","date":"05/11/2022","city":"Zhichu"},
{"id":75,"first_name":"Duncan","last_name":"Rosini","email":"drosini22@oakley.com","company_name":"Viva","designation":"Engineering","address":"17315 Emmet Court","phone_number":"7992194867","date":"01/11/2022","city":"Ngeru"},
{"id":76,"first_name":"Wenona","last_name":"Caudrelier","email":"wcaudrelier23@wordpress.com","company_name":"Cogibox","designation":"Legal","address":"54642 Forest Run Place","phone_number":"2387645243","date":"01/11/2022","city":"Tepal"},
{"id":77,"first_name":"Mozelle","last_name":"Latour","email":"mlatour24@nature.com","company_name":"Kare","designation":"Business Development","address":"205 Dennis Drive","phone_number":"6457769006","date":"05/11/2022","city":"Chujiang"},
{"id":78,"first_name":"Sorcha","last_name":"Fearnall","email":"sfearnall25@dyndns.org","company_name":"Divavu","designation":"Legal","address":"01 Moulton Street","phone_number":"7427260641","date":"04/11/2022","city":"Karanganyar"},
{"id":79,"first_name":"Pembroke","last_name":"Lanphere","email":"planphere26@deviantart.com","company_name":"Flipopia","designation":"Support","address":"95368 Waubesa Avenue","phone_number":"2934380570","date":"03/11/2022","city":"La Victoria"},
{"id":80,"first_name":"Sayre","last_name":"Isaaksohn","email":"sisaaksohn27@blogger.com","company_name":"Oba","designation":"Business Development","address":"702 Manley Way","phone_number":"5323989912","date":"06/11/2022","city":"Huanfeng"},
{"id":81,"first_name":"Larisa","last_name":"Meus","email":"lmeus28@simplemachines.org","company_name":"Babbleset","designation":"Training","address":"82694 Del Mar Junction","phone_number":"6456987770","date":"07/11/2022","city":"Armamar","state":"Viseu"},
{"id":82,"first_name":"Thorn","last_name":"O'Carran","email":"tocarran29@telegraph.co.uk","company_name":"Quinu","designation":"Support","address":"7 Sommers Junction","phone_number":"7503149896","date":"04/11/2022","city":"Tongquan"},
{"id":83,"first_name":"Annalee","last_name":"Croad","email":"acroad2a@delicious.com","company_name":"Yata","designation":"Product Management","address":"6914 Green Plaza","phone_number":"3445189726","date":"05/11/2022","city":"Volokolamsk"},
{"id":84,"first_name":"Roana","last_name":"Miko","email":"rmiko2b@google.nl","company_name":"Wordify","designation":"Accounting","address":"485 Dawn Crossing","phone_number":"9411853266","date":"01/11/2022","city":"Punta Gorda","state":"Florida"},
{"id":85,"first_name":"Constantia","last_name":"Britney","email":"cbritney2c@smugmug.com","company_name":"BlogXS","designation":"Training","address":"288 Del Sol Drive","phone_number":"3191078631","date":"02/11/2022","city":"Fyllingsdalen","state":"Hordaland"},
{"id":86,"first_name":"Fremont","last_name":"Osipov","email":"fosipov2d@auda.org.au","company_name":"Twitterbridge","designation":"Marketing","address":"8 Mariners Cove Crossing","phone_number":"6904401011","date":"02/11/2022","city":"Pombal"},
{"id":87,"first_name":"Jordan","last_name":"Whiteson","email":"jwhiteson2e@list-manage.com","company_name":"Divavu","designation":"Services","address":"4 Tennessee Junction","phone_number":"6095252474","date":"05/11/2022","city":"Dongmaku"},
{"id":88,"first_name":"Timothy","last_name":"Barca","email":"tbarca2f@about.com","company_name":"Photobug","designation":"Engineering","address":"9768 Ridgeview Circle","phone_number":"9629519401","date":"03/11/2022","city":"Boyany"},
{"id":89,"first_name":"Dion","last_name":"Saunter","email":"dsaunter2g@mtv.com","company_name":"JumpXS","designation":"Human Resources","address":"39166 Veith Court","phone_number":"1541134986","date":"02/11/2022","city":"Wierzawice"},
{"id":90,"first_name":"Law","last_name":"Hagwood","email":"lhagwood2h@arstechnica.com","company_name":"Bubbletube","designation":"Legal","address":"0935 Red Cloud Crossing","phone_number":"6945053768","date":"02/11/2022","city":"Cibuah"},
{"id":91,"first_name":"Alverta","last_name":"Lavington","email":"alavington2i@123-reg.co.uk","company_name":"Wikibox","designation":"Accounting","address":"470 Kipling Avenue","phone_number":"9029841930","date":"04/11/2022","city":"Pietermaritzburg"},
{"id":92,"first_name":"Sherm","last_name":"Chadburn","email":"schadburn2j@aboutads.info","company_name":"Brainsphere","designation":"Product Management","address":"4435 Kim Plaza","phone_number":"4706087690","date":"01/11/2022","city":"Zmiyëvka"},
{"id":93,"first_name":"Jessica","last_name":"Grinaway","email":"jgrinaway2k@feedburner.com","company_name":"Twimm","designation":"Engineering","address":"3 Jenifer Parkway","phone_number":"5689190555","date":"05/11/2022","city":"Timurlorong"},
{"id":94,"first_name":"Wayne","last_name":"Shailer","email":"wshailer2l@yolasite.com","company_name":"Quatz","designation":"Marketing","address":"49869 Oakridge Point","phone_number":"7212038619","date":"01/11/2022","city":"Las Flores","state":"Tamaulipas"},
{"id":95,"first_name":"Web","last_name":"Pouck","email":"wpouck2m@1688.com","company_name":"Layo","designation":"Engineering","address":"67 Darwin Alley","phone_number":"1014675733","date":"02/11/2022","city":"Vallehermoso"},
{"id":96,"first_name":"Brnaby","last_name":"Joscelyn","email":"bjoscelyn2n@mashable.com","company_name":"Layo","designation":"Support","address":"5 Gulseth Alley","phone_number":"4494396154","date":"07/11/2022","city":"Phumĭ Véal Srê"},
{"id":97,"first_name":"Nina","last_name":"De Caville","email":"ndecaville2o@shareasale.com","company_name":"Fanoodle","designation":"Marketing","address":"9936 Mosinee Lane","phone_number":"7386376567","date":"06/11/2022","city":"Ganjiachang"},
{"id":98,"first_name":"Nathalie","last_name":"Dust","email":"ndust2p@example.com","company_name":"Mynte","designation":"Services","address":"0235 Nelson Hill","phone_number":"2014249721","date":"07/11/2022","city":"Ning’an"},
{"id":99,"first_name":"Guillaume","last_name":"Collaton","email":"gcollaton2q@goo.ne.jp","company_name":"Zoombox","designation":"Support","address":"1396 Mayer Avenue","phone_number":"8626042205","date":"07/11/2022","city":"Qingyuan"},
{"id":100,"first_name":"Rowney","last_name":"Longcake","email":"rlongcake2r@amazonaws.com","company_name":"Abata","designation":"Legal","address":"4674 Sutherland Avenue","phone_number":"8775463435","date":"01/11/2022","city":"Murcia","state":"Murcia"},
{"id":101,"first_name":"Alejoa","last_name":"Whitbread","email":"awhitbread2s@aboutads.info","company_name":"Gabvine","designation":"Business Development","address":"0 Northland Pass","phone_number":"2679844823","date":"01/11/2022","city":"Elena"},
{"id":102,"first_name":"Dominique","last_name":"Glaum","email":"dglaum2t@xinhuanet.com","company_name":"Twitterwire","designation":"Business Development","address":"55 Columbus Way","phone_number":"4384389091","date":"01/11/2022","city":"Náfplio"},
{"id":103,"first_name":"Ezmeralda","last_name":"Belli","email":"ebelli2u@bing.com","company_name":"Mydeo","designation":"Training","address":"87780 Knutson Lane","phone_number":"9361340776","date":"06/11/2022","city":"Lokuuy"},
{"id":104,"first_name":"Malanie","last_name":"Gilardoni","email":"mgilardoni2v@cpanel.net","company_name":"Aimbo","designation":"Business Development","address":"221 Bluejay Crossing","phone_number":"3382758782","date":"01/11/2022","city":"Agra","state":"Braga"},
{"id":105,"first_name":"Ashbey","last_name":"Laxon","email":"alaxon2w@umich.edu","company_name":"Topdrive","designation":"Marketing","address":"231 Eagle Crest Pass","phone_number":"1932700346","date":"06/11/2022","city":"Péfki"},
{"id":106,"first_name":"Corabel","last_name":"Crumpe","email":"ccrumpe2x@free.fr","company_name":"Kayveo","designation":"Research and Development","address":"90319 Lerdahl Road","phone_number":"8211134658","date":"07/11/2022","city":"Balekambang"},
{"id":107,"first_name":"Dukey","last_name":"Aiton","email":"daiton2y@microsoft.com","company_name":"Photobug","designation":"Research and Development","address":"8520 Rigney Hill","phone_number":"4032254291","date":"02/11/2022","city":"Mocímboa"},
{"id":108,"first_name":"Aeriell","last_name":"Entwistle","email":"aentwistle2z@bbc.co.uk","company_name":"Camido","designation":"Sales","address":"20 American Ash Park","phone_number":"3198121206","date":"01/11/2022","city":"Khodzhi-Gasan"},
{"id":109,"first_name":"Meara","last_name":"McCathy","email":"mmccathy30@purevolume.com","company_name":"Photobug","designation":"Support","address":"9 Mayfield Lane","phone_number":"4954265878","date":"01/11/2022","city":"Sedatigede"},
{"id":110,"first_name":"Krystalle","last_name":"Crunden","email":"kcrunden31@google.ca","company_name":"Meevee","designation":"Research and Development","address":"9050 Bultman Alley","phone_number":"2032768148","date":"01/11/2022","city":"Changshan"},
{"id":111,"first_name":"Cornelius","last_name":"Dalli","email":"cdalli32@tamu.edu","company_name":"Agimba","designation":"Training","address":"2 Bultman Plaza","phone_number":"6269275181","date":"05/11/2022","city":"Caburan"},
{"id":112,"first_name":"Rikki","last_name":"McLeman","email":"rmcleman33@washingtonpost.com","company_name":"Kamba","designation":"Accounting","address":"52158 Hermina Court","phone_number":"3685912896","date":"04/11/2022","city":"Ureshino"},
{"id":113,"first_name":"Devonne","last_name":"McCritichie","email":"dmccritichie34@ca.gov","company_name":"Cogibox","designation":"Sales","address":"94926 8th Drive","phone_number":"4696551554","date":"02/11/2022","city":"Khadan Khāk"},
{"id":114,"first_name":"Lew","last_name":"Cannings","email":"lcannings35@delicious.com","company_name":"Zooveo","designation":"Support","address":"7 Kinsman Point","phone_number":"6104490982","date":"01/11/2022","city":"Abakan"},
{"id":115,"first_name":"Thorstein","last_name":"Button","email":"tbutton36@harvard.edu","company_name":"Dabshots","designation":"Engineering","address":"90 Eagle Crest Road","phone_number":"6954611142","date":"01/11/2022","city":"Mauraro"},
{"id":116,"first_name":"Keenan","last_name":"Bierton","email":"kbierton37@clickbank.net","company_name":"Zoonoodle","designation":"Services","address":"52 Sundown Lane","phone_number":"6737452327","date":"04/11/2022","city":"Gazojak"},
{"id":117,"first_name":"Anna-diane","last_name":"Gilderoy","email":"agilderoy38@squarespace.com","company_name":"Feedfish","designation":"Sales","address":"21 Talmadge Circle","phone_number":"6181242088","date":"01/11/2022","city":"Tanjung Raja"},
{"id":118,"first_name":"Alexi","last_name":"Haking","email":"ahaking39@businesswire.com","company_name":"Roomm","designation":"Accounting","address":"42 Burning Wood Hill","phone_number":"6091749995","date":"07/11/2022","city":"La Banda"},
{"id":119,"first_name":"Bili","last_name":"Rebert","email":"brebert3a@merriam-webster.com","company_name":"Jaxspan","designation":"Research and Development","address":"89 Shopko Court","phone_number":"4325036930","date":"05/11/2022","city":"Heshi"},
{"id":120,"first_name":"Joshua","last_name":"Gatteridge","email":"jgatteridge3b@360.cn","company_name":"Minyx","designation":"Sales","address":"08291 Sundown Way","phone_number":"2417420924","date":"01/11/2022","city":"Le Hochet"},
{"id":121,"first_name":"Kailey","last_name":"Petricek","email":"kpetricek3c@loc.gov","company_name":"Fadeo","designation":"Legal","address":"6983 Kensington Parkway","phone_number":"2898042382","date":"03/11/2022","city":"Shouzhan"},
{"id":122,"first_name":"Keelia","last_name":"Landis","email":"klandis3d@hp.com","company_name":"Blogtags","designation":"Legal","address":"7671 Dunning Pass","phone_number":"2399811960","date":"02/11/2022","city":"San Clemente"},
{"id":123,"first_name":"Samantha","last_name":"Pearce","email":"spearce3e@dailymotion.com","company_name":"Voonte","designation":"Engineering","address":"918 Merry Way","phone_number":"2681443064","date":"05/11/2022","city":"Fentange"},
{"id":124,"first_name":"Cam","last_name":"Sidry","email":"csidry3f@bbc.co.uk","company_name":"Flashspan","designation":"Product Management","address":"68 Kim Junction","phone_number":"1448848385","date":"06/11/2022","city":"Thị Trấn Cẩm Thủy"},
{"id":125,"first_name":"Eustacia","last_name":"Poulney","email":"epoulney3g@com.com","company_name":"Meeveo","designation":"Services","address":"11661 Jay Junction","phone_number":"9086149702","date":"03/11/2022","city":"Hongxing"},
{"id":126,"first_name":"Rutherford","last_name":"Eliff","email":"reliff3h@yale.edu","company_name":"Blogtag","designation":"Human Resources","address":"2 Westridge Terrace","phone_number":"6167845009","date":"03/11/2022","city":"Ntobo"},
{"id":127,"first_name":"Alyss","last_name":"Gumey","email":"agumey3i@github.com","company_name":"Kanoodle","designation":"Services","address":"66 Porter Alley","phone_number":"5438237329","date":"01/11/2022","city":"Nianba"},
{"id":128,"first_name":"Daffy","last_name":"Phette","email":"dphette3j@admin.ch","company_name":"Voonder","designation":"Business Development","address":"3704 Porter Crossing","phone_number":"9652379818","date":"02/11/2022","city":"Chifeng"},
{"id":129,"first_name":"Garrick","last_name":"Wilce","email":"gwilce3k@imgur.com","company_name":"Ooba","designation":"Business Development","address":"44334 Basil Terrace","phone_number":"2567463442","date":"06/11/2022","city":"Palkovice"},
{"id":130,"first_name":"Derrek","last_name":"Muselli","email":"dmuselli3l@reference.com","company_name":"Avamba","designation":"Sales","address":"3 Holy Cross Alley","phone_number":"7105737132","date":"06/11/2022","city":"La Libertad"},
{"id":131,"first_name":"Drusy","last_name":"Teal","email":"dteal3m@imdb.com","company_name":"Trudeo","designation":"Marketing","address":"1 Ridge Oak Place","phone_number":"7637968426","date":"02/11/2022","city":"Mugumu"},
{"id":132,"first_name":"Daniela","last_name":"Dael","email":"ddael3n@homestead.com","company_name":"Livefish","designation":"Human Resources","address":"376 Helena Park","phone_number":"2759599641","date":"07/11/2022","city":"Noeltoko"},
{"id":133,"first_name":"Nehemiah","last_name":"Hagland","email":"nhagland3o@oracle.com","company_name":"Yacero","designation":"Legal","address":"89092 Haas Center","phone_number":"8891803262","date":"04/11/2022","city":"Gualeguay"},
{"id":134,"first_name":"Rahal","last_name":"Keward","email":"rkeward3p@addthis.com","company_name":"Tagopia","designation":"Business Development","address":"68520 Holy Cross Court","phone_number":"8236213609","date":"01/11/2022","city":"Campoalegre"},
{"id":135,"first_name":"Ermin","last_name":"Gaffney","email":"egaffney3q@sciencedaily.com","company_name":"Thoughtworks","designation":"Research and Development","address":"18357 Erie Trail","phone_number":"6242214847","date":"04/11/2022","city":"Zuobude"},
{"id":136,"first_name":"Stace","last_name":"Van Cassel","email":"svancassel3r@dot.gov","company_name":"Realbuzz","designation":"Support","address":"74325 Wayridge Court","phone_number":"4485534346","date":"06/11/2022","city":"Camiling"},
{"id":137,"first_name":"Morty","last_name":"Extance","email":"mextance3s@huffingtonpost.com","company_name":"Zazio","designation":"Research and Development","address":"994 Superior Hill","phone_number":"9628415905","date":"06/11/2022","city":"Asaka"},
{"id":138,"first_name":"Jerry","last_name":"Buten","email":"jbuten3t@myspace.com","company_name":"Zoomzone","designation":"Product Management","address":"5216 Loeprich Park","phone_number":"3375467344","date":"02/11/2022","city":"Jun’an"},
{"id":139,"first_name":"Pooh","last_name":"Fessler","email":"pfessler3u@merriam-webster.com","company_name":"Photolist","designation":"Marketing","address":"9116 Boyd Crossing","phone_number":"8276530372","date":"01/11/2022","city":"Värnamo","state":"Jönköping"},
{"id":140,"first_name":"Kelley","last_name":"Feasby","email":"kfeasby3v@time.com","company_name":"Kare","designation":"Legal","address":"602 Parkside Crossing","phone_number":"1527647566","date":"06/11/2022","city":"Wanasari Baleran"},
{"id":141,"first_name":"Traver","last_name":"Rymer","email":"trymer3w@quantcast.com","company_name":"Realfire","designation":"Business Development","address":"3 Kingsford Pass","phone_number":"2318549857","date":"01/11/2022","city":"Impendle"},
{"id":142,"first_name":"Timotheus","last_name":"Enga","email":"tenga3x@cnet.com","company_name":"Jetpulse","designation":"Research and Development","address":"994 Red Cloud Park","phone_number":"3043595999","date":"07/11/2022","city":"Campinas"},
{"id":143,"first_name":"Doris","last_name":"Hague","email":"dhague3y@reverbnation.com","company_name":"Skipfire","designation":"Human Resources","address":"117 Anhalt Drive","phone_number":"4948547201","date":"01/11/2022","city":"Wanfa"},
{"id":144,"first_name":"Chariot","last_name":"Jameson","email":"cjameson3z@com.com","company_name":"Skipfire","designation":"Sales","address":"02677 Hoard Center","phone_number":"7981565671","date":"02/11/2022","city":"Hor"},
{"id":145,"first_name":"Calla","last_name":"Elford","email":"celford40@slideshare.net","company_name":"Zooveo","designation":"Legal","address":"4 Straubel Circle","phone_number":"5243522093","date":"03/11/2022","city":"Bayog"},
{"id":146,"first_name":"Thedric","last_name":"Lanon","email":"tlanon41@liveinternet.ru","company_name":"Flashspan","designation":"Sales","address":"38 Armistice Road","phone_number":"1411386170","date":"06/11/2022","city":"Hudson Bay","state":"Saskatchewan"},
{"id":147,"first_name":"Francisco","last_name":"Llewellyn","email":"fllewellyn42@woothemes.com","company_name":"Fanoodle","designation":"Sales","address":"44727 Goodland Alley","phone_number":"4815669655","date":"04/11/2022","city":"Cipanas"},
{"id":148,"first_name":"Urbanus","last_name":"Nutbean","email":"unutbean43@netscape.com","company_name":"Livetube","designation":"Services","address":"51 Barnett Pass","phone_number":"4546115569","date":"07/11/2022","city":"Kultayevo"},
{"id":149,"first_name":"Cathyleen","last_name":"Sandom","email":"csandom44@youtu.be","company_name":"Fanoodle","designation":"Engineering","address":"8934 Caliangt Avenue","phone_number":"4412153246","date":"02/11/2022","city":"Neuquén"},
{"id":150,"first_name":"Julie","last_name":"Hanse","email":"jhanse45@newsvine.com","company_name":"Fanoodle","designation":"Human Resources","address":"217 Wayridge Lane","phone_number":"3942658617","date":"01/11/2022","city":"Dungang"},
{"id":151,"first_name":"Delcina","last_name":"Kerby","email":"dkerby46@unicef.org","company_name":"Jaxnation","designation":"Marketing","address":"46 Sunnyside Trail","phone_number":"5165069301","date":"05/11/2022","city":"Mazatenango"},
{"id":152,"first_name":"Kylynn","last_name":"Cotherill","email":"kcotherill47@microsoft.com","company_name":"Skimia","designation":"Accounting","address":"7269 Katie Place","phone_number":"6752109810","date":"07/11/2022","city":"Dahe"},
{"id":153,"first_name":"Augustine","last_name":"Golda","email":"agolda48@uol.com.br","company_name":"Voonte","designation":"Support","address":"0 Saint Paul Drive","phone_number":"9975719599","date":"04/11/2022","city":"Nikolayevskaya"},
{"id":154,"first_name":"Edwin","last_name":"Clair","email":"eclair49@youtu.be","company_name":"Skyvu","designation":"Sales","address":"2727 Emmet Avenue","phone_number":"1408812532","date":"01/11/2022","city":"Sirnasari"},
{"id":155,"first_name":"Shem","last_name":"Sillitoe","email":"ssillitoe4a@slideshare.net","company_name":"Quimba","designation":"Services","address":"3574 Kenwood Point","phone_number":"8723605458","date":"01/11/2022","city":"Ban Lam Luk Ka"},
{"id":156,"first_name":"Oriana","last_name":"Minney","email":"ominney4b@1und1.de","company_name":"Photolist","designation":"Legal","address":"09932 Golf Course Hill","phone_number":"8612098818","date":"06/11/2022","city":"Flores da Cunha"},
{"id":157,"first_name":"Alano","last_name":"Diehn","email":"adiehn4c@vk.com","company_name":"Twiyo","designation":"Human Resources","address":"2230 Del Mar Center","phone_number":"6256281599","date":"02/11/2022","city":"San Pedro One"},
{"id":158,"first_name":"Gwenni","last_name":"Kondratowicz","email":"gkondratowicz4d@ustream.tv","company_name":"Twinte","designation":"Legal","address":"9552 Lakewood Gardens Crossing","phone_number":"6171752287","date":"07/11/2022","city":"San Francisco de Macorís"},
{"id":159,"first_name":"Neala","last_name":"Huston","email":"nhuston4e@nih.gov","company_name":"Kwinu","designation":"Services","address":"76592 Merrick Trail","phone_number":"7628827065","date":"05/11/2022","city":"Beja","state":"Beja"},
{"id":160,"first_name":"De witt","last_name":"Verbeek","email":"dverbeek4f@arstechnica.com","company_name":"Brightbean","designation":"Sales","address":"46 Sunfield Circle","phone_number":"3327076852","date":"05/11/2022","city":"Rangpur"},
{"id":161,"first_name":"Billie","last_name":"Tregonna","email":"btregonna4g@macromedia.com","company_name":"Demivee","designation":"Engineering","address":"6067 Hoepker Street","phone_number":"7414385484","date":"07/11/2022","city":"Banjar Banyualit"},
{"id":162,"first_name":"Gunner","last_name":"Bleasby","email":"gbleasby4h@1und1.de","company_name":"Yadel","designation":"Business Development","address":"20449 Havey Road","phone_number":"8656693245","date":"06/11/2022","city":"Naze"},
{"id":163,"first_name":"Jamey","last_name":"Tabram","email":"jtabram4i@salon.com","company_name":"Dynazzy","designation":"Training","address":"22 Everett Way","phone_number":"2389977280","date":"03/11/2022","city":"Libouchec"},
{"id":164,"first_name":"Glyn","last_name":"Lanphere","email":"glanphere4j@unblog.fr","company_name":"Voolith","designation":"Support","address":"5644 Pankratz Crossing","phone_number":"9532591139","date":"06/11/2022","city":"Allealle"},
{"id":165,"first_name":"Emmerich","last_name":"Serrier","email":"eserrier4k@domainmarket.com","company_name":"Zooveo","designation":"Marketing","address":"08 Canary Park","phone_number":"3557762128","date":"01/11/2022","city":"Eslöv","state":"Skåne"},
{"id":166,"first_name":"West","last_name":"Rudolf","email":"wrudolf4l@constantcontact.com","company_name":"Skinte","designation":"Business Development","address":"999 Onsgard Point","phone_number":"9272336306","date":"06/11/2022","city":"Zaraza"},
{"id":167,"first_name":"Jaymee","last_name":"Gilluley","email":"jgilluley4m@ameblo.jp","company_name":"Voomm","designation":"Legal","address":"1449 Melby Way","phone_number":"2268725390","date":"07/11/2022","city":"Yuhuangding"},
{"id":168,"first_name":"Wake","last_name":"Heinreich","email":"wheinreich4n@ebay.co.uk","company_name":"Yodo","designation":"Business Development","address":"7960 Aberg Center","phone_number":"4978328307","date":"03/11/2022","city":"Patzicía"},
{"id":169,"first_name":"Sig","last_name":"Arderne","email":"sarderne4o@cbslocal.com","company_name":"Leenti","designation":"Training","address":"4168 Delladonna Junction","phone_number":"2124995002","date":"03/11/2022","city":"Gómez"},
{"id":170,"first_name":"Cristian","last_name":"Huncoot","email":"chuncoot4p@go.com","company_name":"Twitternation","designation":"Product Management","address":"23 Westend Plaza","phone_number":"1869752611","date":"06/11/2022","city":"Cibeureum"},
{"id":171,"first_name":"Zorana","last_name":"Marklin","email":"zmarklin4q@patch.com","company_name":"Ozu","designation":"Support","address":"21 Blaine Junction","phone_number":"5255610881","date":"04/11/2022","city":"Fāqūs"},
{"id":172,"first_name":"Dougie","last_name":"Von Welden","email":"dvonwelden4r@feedburner.com","company_name":"Omba","designation":"Services","address":"05660 Havey Lane","phone_number":"2413861321","date":"01/11/2022","city":"Kandangan"},
{"id":173,"first_name":"Garwood","last_name":"Ryrie","email":"gryrie4s@jigsy.com","company_name":"Meemm","designation":"Accounting","address":"201 Village Drive","phone_number":"8568300671","date":"01/11/2022","city":"Jetafe"},
{"id":174,"first_name":"Leanna","last_name":"Harce","email":"lharce4t@mysql.com","company_name":"Voolia","designation":"Product Management","address":"478 Russell Point","phone_number":"7024238046","date":"06/11/2022","city":"Gramoteino"},
{"id":175,"first_name":"Terry","last_name":"Coopman","email":"tcoopman4u@europa.eu","company_name":"Dabtype","designation":"Research and Development","address":"7 Vernon Terrace","phone_number":"2386939980","date":"06/11/2022","city":"Nynäshamn","state":"Stockholm"},
{"id":176,"first_name":"Bathsheba","last_name":"Guidini","email":"bguidini4v@1und1.de","company_name":"Plajo","designation":"Support","address":"1 Hooker Point","phone_number":"9651857504","date":"03/11/2022","city":"Balgarevo"},
{"id":177,"first_name":"Annmarie","last_name":"Pioch","email":"apioch4w@columbia.edu","company_name":"Oyoyo","designation":"Support","address":"7871 Pawling Circle","phone_number":"3772916971","date":"05/11/2022","city":"Sparwood","state":"British Columbia"},
{"id":178,"first_name":"Vonnie","last_name":"MacCawley","email":"vmaccawley4x@ox.ac.uk","company_name":"Vinder","designation":"Legal","address":"1533 Pawling Plaza","phone_number":"6976158804","date":"06/11/2022","city":"Dalupaon"},
{"id":179,"first_name":"Mona","last_name":"Atto","email":"matto4y@theatlantic.com","company_name":"Eare","designation":"Marketing","address":"15 Roth Crossing","phone_number":"5359462308","date":"06/11/2022","city":"Kota Trieng"},
{"id":180,"first_name":"Gerry","last_name":"Skillington","email":"gskillington4z@illinois.edu","company_name":"Talane","designation":"Support","address":"5 Lillian Way","phone_number":"9561156113","date":"05/11/2022","city":"Al Ḩaffah"},
{"id":181,"first_name":"Joachim","last_name":"Acey","email":"jacey50@europa.eu","company_name":"Vidoo","designation":"Product Management","address":"86 1st Crossing","phone_number":"5245948202","date":"01/11/2022","city":"Viangxai"},
{"id":182,"first_name":"Cleopatra","last_name":"Chalmers","email":"cchalmers51@a8.net","company_name":"Aimbu","designation":"Business Development","address":"989 Lindbergh Court","phone_number":"5039363857","date":"06/11/2022","city":"Batgrām"},
{"id":183,"first_name":"Weston","last_name":"Di Ruggero","email":"wdiruggero52@usatoday.com","company_name":"Jayo","designation":"Legal","address":"40799 Vidon Way","phone_number":"2107305883","date":"03/11/2022","city":"Chaman"},
{"id":184,"first_name":"Xylia","last_name":"Hagstone","email":"xhagstone53@istockphoto.com","company_name":"Oyoba","designation":"Legal","address":"68062 Bobwhite Park","phone_number":"1035993723","date":"07/11/2022","city":"Carumas"},
{"id":185,"first_name":"Rodina","last_name":"Kneath","email":"rkneath54@mozilla.org","company_name":"Minyx","designation":"Business Development","address":"5 Pleasure Avenue","phone_number":"6986430209","date":"06/11/2022","city":"Eastern Suburbs Mc","state":"New South Wales"},
{"id":186,"first_name":"Gweneth","last_name":"Bauld","email":"gbauld55@t-online.de","company_name":"Abata","designation":"Legal","address":"9252 Forest Run Lane","phone_number":"6131084259","date":"02/11/2022","city":"Caicó"},
{"id":187,"first_name":"Derward","last_name":"Whitten","email":"dwhitten56@mysql.com","company_name":"Yoveo","designation":"Business Development","address":"087 Dahle Drive","phone_number":"8229471861","date":"01/11/2022","city":"Wuxing"},
{"id":188,"first_name":"Lesli","last_name":"Rapkins","email":"lrapkins57@ustream.tv","company_name":"Buzzster","designation":"Accounting","address":"2 Mitchell Plaza","phone_number":"8318185655","date":"06/11/2022","city":"Verkhnyaya Khava"},
{"id":189,"first_name":"Caldwell","last_name":"Pipe","email":"cpipe58@nationalgeographic.com","company_name":"Yozio","designation":"Support","address":"8 Fairview Court","phone_number":"3217946645","date":"03/11/2022","city":"Solna","state":"Stockholm"},
{"id":190,"first_name":"Pat","last_name":"Wasson","email":"pwasson59@github.com","company_name":"Linkbridge","designation":"Training","address":"19 Eagan Way","phone_number":"4027357691","date":"03/11/2022","city":"Lincoln","state":"Nebraska"},
{"id":191,"first_name":"Lianna","last_name":"Juschke","email":"ljuschke5a@go.com","company_name":"Meejo","designation":"Training","address":"62639 Merrick Drive","phone_number":"6532510205","date":"06/11/2022","city":"Hagonoy"},
{"id":192,"first_name":"Ulrich","last_name":"Nern","email":"unern5b@abc.net.au","company_name":"Vinte","designation":"Accounting","address":"83 Roxbury Plaza","phone_number":"6658992068","date":"04/11/2022","city":"Mouriscas","state":"Santarém"},
{"id":193,"first_name":"Dennet","last_name":"McAlpin","email":"dmcalpin5c@google.es","company_name":"Topicblab","designation":"Engineering","address":"52 Fallview Terrace","phone_number":"6954726186","date":"02/11/2022","city":"Fontenay-sous-Bois","state":"Île-de-France"},
{"id":194,"first_name":"Janice","last_name":"Beauly","email":"jbeauly5d@deviantart.com","company_name":"Meetz","designation":"Engineering","address":"17629 Manufacturers Way","phone_number":"8912564242","date":"03/11/2022","city":"Älvängen","state":"Västra Götaland"},
{"id":195,"first_name":"Abner","last_name":"Bury","email":"abury5e@t.co","company_name":"Feedbug","designation":"Human Resources","address":"69299 Esker Junction","phone_number":"4538466052","date":"05/11/2022","city":"Khashuri"},
{"id":196,"first_name":"Darcey","last_name":"Huddles","email":"dhuddles5f@addthis.com","company_name":"Mita","designation":"Sales","address":"39 Swallow Junction","phone_number":"7901389088","date":"04/11/2022","city":"Zhangfang"},
{"id":197,"first_name":"Emmott","last_name":"De Bruyne","email":"edebruyne5g@noaa.gov","company_name":"Gabcube","designation":"Business Development","address":"238 Southridge Point","phone_number":"3772411765","date":"02/11/2022","city":"Trablice"},
{"id":198,"first_name":"Andonis","last_name":"Kendrew","email":"akendrew5h@dropbox.com","company_name":"Roombo","designation":"Services","address":"5631 Sycamore Junction","phone_number":"6249175480","date":"04/11/2022","city":"Girihieum"},
{"id":199,"first_name":"Stefanie","last_name":"Silman","email":"ssilman5i@unesco.org","company_name":"Livetube","designation":"Support","address":"248 Crest Line Lane","phone_number":"5053511443","date":"03/11/2022","city":"Sabugo","state":"Lisboa"},
{"id":200,"first_name":"Shane","last_name":"Clout","email":"sclout5j@independent.co.uk","company_name":"Skyble","designation":"Services","address":"6 Milwaukee Lane","phone_number":"6229803603","date":"04/11/2022","city":"Daping"}]